to_do_cli/__init__.py
to_do_cli/main.py
taskninja-0.1.0.dist-info/METADATA
taskninja-0.1.0.dist-info/WHEEL
taskninja-0.1.0.dist-info/entry_points.txt
taskninja-0.1.0.dist-info/top_level.txt
taskninja-0.1.0.dist-info/RECORD
