Metadata-Version: 2.2
Name: taskninja
Version: 0.1.0
Summary: A simple CLI-based to-do list application
Author: Manish
Requires-Dist: typer
